README.md
setup.py
docums_enumerate_headings_plugin/__init__.py
docums_enumerate_headings_plugin/exclude.py
docums_enumerate_headings_plugin/heading.py
docums_enumerate_headings_plugin/html_page.py
docums_enumerate_headings_plugin/plugin.py
docums_enumerate_headings_plugin.egg-info/PKG-INFO
docums_enumerate_headings_plugin.egg-info/SOURCES.txt
docums_enumerate_headings_plugin.egg-info/dependency_links.txt
docums_enumerate_headings_plugin.egg-info/entry_points.txt
docums_enumerate_headings_plugin.egg-info/requires.txt
docums_enumerate_headings_plugin.egg-info/top_level.txt