Metadata-Version: 2.1
Name: docums-enumerate-headings-plugin
Version: 0.5.0
Summary: Docums Plugin to enumerate the headings (h1-h6) across site pages
Home-page: https://github.com/khanhduy1407/docums-enumerate-headings-plugin.git
Author: NKDuy
Author-email: kn145660@gmail.com
License: MIT
Keywords: docums enumerate headings plugin
Platform: UNKNOWN
Classifier: Intended Audience :: Developers
Classifier: Intended Audience :: Information Technology
Classifier: License :: OSI Approved :: MIT License
Classifier: Programming Language :: Python
Classifier: Programming Language :: Python :: 3 :: Only
Classifier: Programming Language :: Python :: 3.7
Classifier: Programming Language :: Python :: 3.8
Classifier: Programming Language :: Python :: 3.9
Classifier: Programming Language :: Python :: 3.10
Requires-Python: >=3.5
